README.md
scholar_network/__init__.py
scholar_network/helpers.py
scholar_network/models.py
scholar_network/scraping.py
scholar_network-0.2.6.dist-info/WHEEL
scholar_network-0.2.6.dist-info/METADATA
scholar_network-0.2.6.dist-info/RECORD
