Metadata-Version: 2.1
Name: scholar-network
Version: 0.2.6
Summary: Graph Network Analysis for scraping Google Scholar authors.
License: MIT
Author: Nick Anthony
Author-email: nanthony007@gmail.com
Requires-Python: >=3.10,<3.11
Classifier: License :: OSI Approved :: MIT License
Classifier: Programming Language :: Python :: 3
Classifier: Programming Language :: Python :: 3.10
Requires-Dist: selenium (>=4.3.0,<5.0.0)
